il.py
il-0.3.dist-info/LICENSE
il-0.3.dist-info/METADATA
il-0.3.dist-info/WHEEL
il-0.3.dist-info/top_level.txt
il-0.3.dist-info/RECORD
