Metadata-Version: 2.1
Name: il
Version: 0.3
Summary: Inline assembly in Python
Home-page: https://github.com/askervin/python-il
Author: Antti Kervinen
Author-email: antti.kervinen@gmail.com
License: UNKNOWN
Platform: UNKNOWN
Classifier: Programming Language :: Python :: 3
Classifier: License :: OSI Approved :: MIT License
Classifier: Operating System :: OS Independent
